pclearn/2dCircularConvolution.sce
pclearn/2dLinearConvolution.sce
pclearn/BrightnessEnhance.sce
pclearn/BrightnessReduce.sce
pclearn/BtcImageCompression.sce
pclearn/CircularAsLineConvo.sce
pclearn/CircularCorrelation.sce
pclearn/ContrastManipulation.sce
pclearn/DFTgray.sce
pclearn/DialationErosion.sce
pclearn/EdgeDetection.sce
pclearn/GaussianFilterFun.sce
pclearn/GaussianFun.sce
pclearn/GrayLevelScaling.sce
pclearn/ImageAddSub.sce
pclearn/ImageMulDiv.sce
pclearn/KLtransformation.sce
pclearn/LinearAutoCorrelation.sce
pclearn/LinearCrossCorrelation.sce
pclearn/OpeningClose.sce
pclearn/RGBextract.sce
pclearn/SeperateImageRGB.sce
pclearn/Threshold.sce
pclearn/__init__.py
pclearn/folder.py
pclearn/negativeImage.sce
pclearn-0.24.dist-info/METADATA
pclearn-0.24.dist-info/WHEEL
pclearn-0.24.dist-info/entry_points.txt
pclearn-0.24.dist-info/top_level.txt
pclearn-0.24.dist-info/RECORD
