Metadata-Version: 2.1
Name: pclearn
Version: 0.24
Summary: A package to create folders and store .py files
Author: jerrry
Author-email: jerryjones23@gmail.com
Classifier: Programming Language :: Python :: 3
Classifier: License :: OSI Approved :: MIT License
Classifier: Operating System :: OS Independent
Requires-Python: >=3.6
